llm_http_api/__init__.py
llm_http_api/__main__.py
llm_http_api/server/__init__.py
llm_http_api/server/fastapi.py
llm_http_api/server/assistants/__init__.py
llm_http_api/server/audio/__init__.py
llm_http_api/server/chat/__init__.py
llm_http_api/server/embeddings/__init__.py
llm_http_api/server/embeddings/create_embedding.py
llm_http_api/server/files/__init__.py
llm_http_api/server/fine_tuning/__init__.py
llm_http_api/server/images/__init__.py
llm_http_api/server/messages/__init__.py
llm_http_api/server/models/__init__.py
llm_http_api/server/models/delete_model.py
llm_http_api/server/models/list_models.py
llm_http_api/server/models/retrieve_model.py
llm_http_api/server/moderations/__init__.py
llm_http_api/server/probes/__init__.py
llm_http_api/server/root/__init__.py
llm_http_api/server/runs/__init__.py
llm_http_api/server/swagger/__init__.py
llm_http_api/server/threads/__init__.py
llm_http_api-0.0.2.dist-info/LICENSE
llm_http_api-0.0.2.dist-info/METADATA
llm_http_api-0.0.2.dist-info/WHEEL
llm_http_api-0.0.2.dist-info/entry_points.txt
llm_http_api-0.0.2.dist-info/top_level.txt
llm_http_api-0.0.2.dist-info/RECORD
